{"commitInfo":{"timestamp":1696025273930,"operation":"WRITE","operationParameters":{"mode":"ErrorIfExists","partitionBy":"[]"},"isolationLevel":"Serializable","isBlindAppend":true,"operationMetrics":{"numFiles":"1","numOutputRows":"210384","numOutputBytes":"1146467"},"engineInfo":"Apache-Spark/3.3.0 Delta-Lake/2.2.0","txnId":"4421492f-a134-4f33-881c-f09d2258fab4"}}
{"protocol":{"minReaderVersion":1,"minWriterVersion":2}}
{"metaData":{"id":"466806cf-f6ff-433d-b5c2-db2db525cdc9","format":{"provider":"parquet","options":{}},"schemaString":"{\"type\":\"struct\",\"fields\":[{\"name\":\"latitude\",\"type\":\"double\",\"nullable\":true,\"metadata\":{}},{\"name\":\"longitude\",\"type\":\"double\",\"nullable\":true,\"metadata\":{}},{\"name\":\"time\",\"type\":\"string\",\"nullable\":true,\"metadata\":{}},{\"name\":\"temperature_2m\",\"type\":\"double\",\"nullable\":true,\"metadata\":{}}]}","partitionColumns":[],"configuration":{},"createdTime":1696025270566}}
{"add":{"path":"part-00000-9b407478-3b11-43f3-9e43-09b6246f553b-c000.snappy.parquet","partitionValues":{},"size":1146467,"modificationTime":1696025273758,"dataChange":true,"stats":"{\"numRecords\":210384,\"minValues\":{\"latitude\":13.0,\"longitude\":-149.9,\"time\":\"2019-01-01T00:00\",\"temperature_2m\":-26.6},\"maxValues\":{\"latitude\":61.199997,\"longitude\":77.600006,\"time\":\"2022-12-31T23:00\",\"temperature_2m\":40.2},\"nullCount\":{\"latitude\":0,\"longitude\":0,\"time\":0,\"temperature_2m\":0}}"}}
